<images>
<image id='N8140'><typeObjet>Sceau</typeObjet>
<nom_fichier>N8140.jpg</nom_fichier>
<fid_Note>N8140</fid_Note>
</image>
<image id='N8151'><typeObjet>Sceau</typeObjet>
<nom_fichier>N8151.jpg</nom_fichier>
<fid_Note>N8151</fid_Note>
</image>
<image id='N8152'><typeObjet>Sceau</typeObjet>
<nom_fichier>N8152.jpg</nom_fichier>
<fid_Note>N8152</fid_Note>
</image>
<image id='N8153'><typeObjet>Sceau</typeObjet>
<nom_fichier>N8153.jpg</nom_fichier>
<fid_Note>N8153</fid_Note>
</image>
<image id='N8154'><typeObjet>Sceau</typeObjet>
<nom_fichier>N8154.jpg</nom_fichier>
<fid_Note>N8154</fid_Note>
</image>
<image id='N8155'><typeObjet>Sceau</typeObjet>
<nom_fichier>N8155.jpg</nom_fichier>
<fid_Note>N8155</fid_Note>
</image>
<image id='N8156'><typeObjet>Sceau</typeObjet>
<nom_fichier>N8156.jpg</nom_fichier>
<fid_Note>N8156</fid_Note>
</image>
<image id='N8158'><typeObjet>Sceau</typeObjet>
<nom_fichier>N8158.jpg</nom_fichier>
<fid_Note>N8158</fid_Note>
</image>
<image id='N8159'><typeObjet>Sceau</typeObjet>
<nom_fichier>N8159.jpg</nom_fichier>
<fid_Note>N8159</fid_Note>
</image>
<image id='N8160'><typeObjet>Sceau</typeObjet>
<nom_fichier>N8160.jpg</nom_fichier>
<fid_Note>N8160</fid_Note>
</image>
<image id='N8161'><typeObjet>Sceau</typeObjet>
<nom_fichier>N8161.jpg</nom_fichier>
<fid_Note>N8161</fid_Note>
</image>
<image id='N8162'><typeObjet>Sceau</typeObjet>
<nom_fichier>N8162.jpg</nom_fichier>
<fid_Note>N8162</fid_Note>
</image>
<image id='N8163'><typeObjet>Sceau</typeObjet>
<nom_fichier>N8163.jpg</nom_fichier>
<fid_Note>N8163</fid_Note>
</image>
<image id='N8164'><typeObjet>Sceau</typeObjet>
<nom_fichier>N8164.jpg</nom_fichier>
<fid_Note>N8164</fid_Note>
</image>
<image id='N8165'><typeObjet>Sceau</typeObjet>
<nom_fichier>N8165.jpg</nom_fichier>
<fid_Note>N8165</fid_Note>
</image>
<image id='N8166'><typeObjet>Sceau</typeObjet>
<nom_fichier>N8166.jpg</nom_fichier>
<fid_Note>N8166</fid_Note>
</image>
<image id='N8167'><typeObjet>Sceau</typeObjet>
<nom_fichier>N8167.jpg</nom_fichier>
<fid_Note>N8167</fid_Note>
</image>
<image id='N8178'><typeObjet>Sceau</typeObjet>
<nom_fichier>N8178.jpg</nom_fichier>
<fid_Note>N8178</fid_Note>
</image>
<image id='N8181'><typeObjet>Sceau</typeObjet>
<nom_fichier>N8181.jpg</nom_fichier>
<fid_Note>N8181</fid_Note>
</image>
<image id='N8266'><typeObjet>Sceau</typeObjet>
<nom_fichier>N8266.jpg</nom_fichier>
<fid_Note>N8266</fid_Note>
</image>
<image id='N8422'><typeObjet>Sceau</typeObjet>
<nom_fichier>N8422.jpg</nom_fichier>
<fid_Note>N8422</fid_Note>
</image>
<image id='N8423'><typeObjet>Sceau</typeObjet>
<nom_fichier>N8423.jpg</nom_fichier>
<fid_Note>N8423</fid_Note>
</image>
<image id='N8441'><typeObjet>Sceau</typeObjet>
<nom_fichier>N8441.jpg</nom_fichier>
<fid_Note>N8441</fid_Note>
</image>
<image id='N8480a'><typeObjet>Sceau</typeObjet>
<nom_fichier>N8480a.jpg</nom_fichier>
<fid_Note>N8480a</fid_Note>
</image>
<image id='N8480b'><typeObjet>Sceau</typeObjet>
<nom_fichier>N8480b.jpg</nom_fichier>
<fid_Note>N8480b</fid_Note>
</image>
<image id='N8480c'><typeObjet>Sceau</typeObjet>
<nom_fichier>N8480c.jpg</nom_fichier>
<fid_Note>N8480c</fid_Note>
</image>
<image id='N8480d'><typeObjet>Sceau</typeObjet>
<nom_fichier>N8480d.jpg</nom_fichier>
<fid_Note>N8480d</fid_Note>
</image>
<image id='N8480e'><typeObjet>Sceau</typeObjet>
<nom_fichier>N8480e.jpg</nom_fichier>
<fid_Note>N8480e</fid_Note>
</image>
<image id='N8481'><typeObjet>Sceau</typeObjet>
<nom_fichier>N8481.jpg</nom_fichier>
<fid_Note>N8481</fid_Note>
</image>
<image id='N8482'><typeObjet>Sceau</typeObjet>
<nom_fichier>N8482.jpg</nom_fichier>
<fid_Note>N8482</fid_Note>
</image>
<image id='N8483'><typeObjet>Sceau</typeObjet>
<nom_fichier>N8483.jpg</nom_fichier>
<fid_Note>N8483</fid_Note>
</image>
<image id='N8484'><typeObjet>Sceau</typeObjet>
<nom_fichier>N8484.jpg</nom_fichier>
<fid_Note>N8484</fid_Note>
</image>
<image id='N8485'><typeObjet>Sceau</typeObjet>
<nom_fichier>N8485.jpg</nom_fichier>
<fid_Note>N8485</fid_Note>
</image>
<image id='N8486'><typeObjet>Sceau</typeObjet>
<nom_fichier>N8486.jpg</nom_fichier>
<fid_Note>N8486</fid_Note>
</image>
<image id='N8487'><typeObjet>Sceau</typeObjet>
<nom_fichier>N8487.jpg</nom_fichier>
<fid_Note>N8487</fid_Note>
</image>
<image id='N8488'><typeObjet>Sceau</typeObjet>
<nom_fichier>N8488.jpg</nom_fichier>
<fid_Note>N8488</fid_Note>
</image>
<image id='N8489'><typeObjet>Sceau</typeObjet>
<nom_fichier>N8489.jpg</nom_fichier>
<fid_Note>N8489</fid_Note>
</image>
<image id='N8490'><typeObjet>Sceau</typeObjet>
<nom_fichier>N8490.jpg</nom_fichier>
<fid_Note>N8490</fid_Note>
</image>
<image id='N8491'><typeObjet>Sceau</typeObjet>
<nom_fichier>N8491.jpg</nom_fichier>
<fid_Note>N8491</fid_Note>
</image>
<image id='N8492'><typeObjet>Sceau</typeObjet>
<nom_fichier>N8492.jpg</nom_fichier>
<fid_Note>N8492</fid_Note>
</image>
<image id='N8493'><typeObjet>Sceau</typeObjet>
<nom_fichier>N8493.jpg</nom_fichier>
<fid_Note>N8493</fid_Note>
</image>
<image id='N8494'><typeObjet>Sceau</typeObjet>
<nom_fichier>N8494.jpg</nom_fichier>
<fid_Note>N8494</fid_Note>
</image>
<image id='N8495'><typeObjet>Sceau</typeObjet>
<nom_fichier>N8495.jpg</nom_fichier>
<fid_Note>N8495</fid_Note>
</image>
<image id='N8496'><typeObjet>Sceau</typeObjet>
<nom_fichier>N8496.jpg</nom_fichier>
<fid_Note>N8496</fid_Note>
</image>
<image id='N8497'><typeObjet>Sceau</typeObjet>
<nom_fichier>N8497.jpg</nom_fichier>
<fid_Note>N8497</fid_Note>
</image>
<image id='N8498'><typeObjet>Sceau</typeObjet>
<nom_fichier>N8498.jpg</nom_fichier>
<fid_Note>N8498</fid_Note>
</image>
<image id='N8499'><typeObjet>Sceau</typeObjet>
<nom_fichier>N8499.jpg</nom_fichier>
<fid_Note>N8499</fid_Note>
</image>
<image id='N8500'><typeObjet>Sceau</typeObjet>
<nom_fichier>N8500.jpg</nom_fichier>
<fid_Note>N8500</fid_Note>
</image>
<image id='N8501'><typeObjet>Sceau</typeObjet>
<nom_fichier>N8501.jpg</nom_fichier>
<fid_Note>N8501</fid_Note>
</image>
<image id='N8502'><typeObjet>Sceau</typeObjet>
<nom_fichier>N8502.jpg</nom_fichier>
<fid_Note>N8502</fid_Note>
</image>
<image id='N8503'><typeObjet>Sceau</typeObjet>
<nom_fichier>N8503.jpg</nom_fichier>
<fid_Note>N8503</fid_Note>
</image>
<image id='N8504'><typeObjet>Sceau</typeObjet>
<nom_fichier>N8504.jpg</nom_fichier>
<fid_Note>N8504</fid_Note>
</image>
<image id='N8545'><typeObjet>Sceau</typeObjet>
<nom_fichier>N8545.jpg</nom_fichier>
<fid_Note>N8545</fid_Note>
</image>
<image id='N8579'><typeObjet>Sceau</typeObjet>
<nom_fichier>N8579.jpg</nom_fichier>
<fid_Note>N8579</fid_Note>
</image>
<image id='N8596'><typeObjet>Sceau</typeObjet>
<nom_fichier>N8596.jpg</nom_fichier>
<fid_Note>N8596</fid_Note>
</image>
<image id='N8608'><typeObjet>Sceau</typeObjet>
<nom_fichier>N8608.jpg</nom_fichier>
<fid_Note>N8608</fid_Note>
</image>
<image id='N9082'><typeObjet>Sceau</typeObjet>
<nom_fichier>N9082.jpg</nom_fichier>
<fid_Note>N9082</fid_Note>
</image>
<image id='N9088a'><typeObjet>Sceau</typeObjet>
<nom_fichier>N9088a.jpg</nom_fichier>
<fid_Note>N9088a</fid_Note>
</image>
<image id='N9088b'><typeObjet>Sceau</typeObjet>
<nom_fichier>N9088b.jpg</nom_fichier>
<fid_Note>N9088b</fid_Note>
</image>
<image id='N8203'><typeObjet>Sceau</typeObjet>
<nom_fichier>N8203.jpg</nom_fichier>
<fid_Note>N8203</fid_Note>
</image>
<image id='N8354'><typeObjet>Sceau</typeObjet>
<nom_fichier>N8354.jpg</nom_fichier>
<fid_Note>N8354</fid_Note>
</image>
<image id='N8157'><typeObjet>Sceau</typeObjet>
<nom_fichier>N8157.jpg</nom_fichier>
<fid_Note>N8157</fid_Note>
</image>
<image id='N8280'><typeObjet>Sceau</typeObjet>
<nom_fichier>N8280.jpg</nom_fichier>
<fid_Note>N8280</fid_Note>
</image>
</images>
